odoo/addons/account_move_tier_validation/README.rst
odoo/addons/account_move_tier_validation/__init__.py
odoo/addons/account_move_tier_validation/__manifest__.py
odoo/addons/account_move_tier_validation/i18n/account_move_tier_validation.pot
odoo/addons/account_move_tier_validation/i18n/ca.po
odoo/addons/account_move_tier_validation/i18n/es.po
odoo/addons/account_move_tier_validation/i18n/es_PA.po
odoo/addons/account_move_tier_validation/i18n/sv.po
odoo/addons/account_move_tier_validation/i18n/zh_CN.po
odoo/addons/account_move_tier_validation/models/__init__.py
odoo/addons/account_move_tier_validation/models/account_move.py
odoo/addons/account_move_tier_validation/models/tier_definition.py
odoo/addons/account_move_tier_validation/readme/CONFIGURE.rst
odoo/addons/account_move_tier_validation/readme/CONTRIBUTORS.rst
odoo/addons/account_move_tier_validation/readme/DESCRIPTION.rst
odoo/addons/account_move_tier_validation/readme/INSTALL.rst
odoo/addons/account_move_tier_validation/readme/USAGE.rst
odoo/addons/account_move_tier_validation/static/description/icon.png
odoo/addons/account_move_tier_validation/static/description/index.html
odoo/addons/account_move_tier_validation/tests/__init__.py
odoo/addons/account_move_tier_validation/tests/common.py
odoo/addons/account_move_tier_validation/tests/test_tier_validation.py
odoo/addons/account_move_tier_validation/tests/tier_validation_tester.py
odoo/addons/account_move_tier_validation/views/account_move_view.xml
odoo14_addon_account_move_tier_validation-14.0.1.1.0.dist-info/METADATA
odoo14_addon_account_move_tier_validation-14.0.1.1.0.dist-info/WHEEL
odoo14_addon_account_move_tier_validation-14.0.1.1.0.dist-info/top_level.txt
odoo14_addon_account_move_tier_validation-14.0.1.1.0.dist-info/RECORD
